iso6346/__init__.py
iso6346_containers-0.2.1.dist-info/LICENSE
iso6346_containers-0.2.1.dist-info/METADATA
iso6346_containers-0.2.1.dist-info/WHEEL
iso6346_containers-0.2.1.dist-info/top_level.txt
iso6346_containers-0.2.1.dist-info/RECORD
