Metadata-Version: 2.1
Name: iso6346-containers
Version: 0.2.1
Summary: ISO 6346 Freight containers: Coding, identification and marking.
Author-email: Damien Bezborodov <dbezborodov@gmail.com>
License: BSD 3-Clause License
Project-URL: Homepage, https://github.com/bezborodow/iso6346py
Project-URL: Bug Tracker, https://github.com/bezborodow/iso6346py/issues
Project-URL: Documentation, https://iso6346-containers.readthedocs.io/en/latest/
Keywords: iso6346
Classifier: Programming Language :: Python :: 3
Classifier: License :: OSI Approved :: BSD License
Classifier: Operating System :: OS Independent
Requires-Python: >=3.7
License-File: LICENSE
